remotecall/__init__.py
remotecall/__main__.py
remotecall/_meta.py
remotecall/client.py
remotecall/clientfactory.py
remotecall/codecs.py
remotecall/endpoint.py
remotecall/errors.py
remotecall/exceptions.py
remotecall/gethandler.py
remotecall/posthandler.py
remotecall/requesthandler.py
remotecall/response.py
remotecall/server.py
remotecall/utils.py
remotecall/authentication/__init__.py
remotecall/authentication/authenticator.py
remotecall/constants/__init__.py
remotecall/constants/headers.py
remotecall/constants/statuscodes.py
remotecall/extras/__init__.py
remotecall/extras/imagecodec.py
remotecall/extras/numpycodec.py
remotecall-0.4.1.dist-info/licenses/LICENSE
remotecall-0.4.1.dist-info/METADATA
remotecall-0.4.1.dist-info/WHEEL
remotecall-0.4.1.dist-info/entry_points.txt
remotecall-0.4.1.dist-info/top_level.txt
remotecall-0.4.1.dist-info/RECORD
