Metadata-Version: 2.4
Name: remotecall
Version: 0.4.1
Summary: The module provides functionality to expose Python functions to be called remotely over ethernet.
Home-page: https://gitlab.com/slaine/remotecall.git/
Author: Sami Laine
Author-email: sami.jy.laine@gmail.com
License: BSD-3-Clause
License-File: LICENSE
Requires-Dist: requests>=2.28.1
Provides-Extra: test
Requires-Dist: pytest; extra == "test"
Provides-Extra: full
Requires-Dist: numpy; extra == "full"
Requires-Dist: pillow; extra == "full"
Provides-Extra: numpycodec
Requires-Dist: numpy; extra == "numpycodec"
Provides-Extra: imagecodec
Requires-Dist: pillow; extra == "imagecodec"
Dynamic: author
Dynamic: author-email
Dynamic: description
Dynamic: description-content-type
Dynamic: home-page
Dynamic: license
Dynamic: license-file
Dynamic: provides-extra
Dynamic: requires-dist
Dynamic: summary
